xyndra_core/__init__.py
xyndra_function_core-0.1.3.dist-info/METADATA
xyndra_function_core-0.1.3.dist-info/WHEEL
xyndra_function_core-0.1.3.dist-info/top_level.txt
xyndra_function_core-0.1.3.dist-info/RECORD
