Metadata-Version: 2.1
Name: xyndra-function-core
Version: 0.1.3
Summary: A core with all my useful functions.
Home-page: UNKNOWN
Author: Xyndra
Author-email: UNKNOWN
License: UNKNOWN
Keywords: python,arrays,easy function
Platform: UNKNOWN
Classifier: Development Status :: 5 - Production/Stable
Classifier: Programming Language :: Python :: 3
Classifier: Operating System :: Unix
Classifier: Operating System :: MacOS :: MacOS X
Classifier: Operating System :: Microsoft :: Windows
Requires-Dist: numpy
